nonebot_plugin_zzzpanel-0.1.6.dist-info/METADATA
nonebot_plugin_zzzpanel-0.1.6.dist-info/WHEEL
nonebot_plugin_zzzpanel-0.1.6.dist-info/entry_points.txt
nonebot_plugin_zzzpanel/__init__.py
nonebot_plugin_zzzpanel/config.py
nonebot_plugin_zzzpanel/intopng.py
nonebot_plugin_zzzpanel/utils.py
nonebot_plugin_zzzpanel-0.1.6.dist-info/RECORD
