Metadata-Version: 2.1
Name: nonebot_plugin_zzzpanel
Version: 0.1.6
Summary: 绝区零角色数据获取插件
Author-Email: STESmly <3549337307@qq.com>
License: MIT
Project-URL: Homepage, https://github.com/STESmly/nonebot_plugin_zzzpanel
Requires-Python: >=3.11
Requires-Dist: httpx>=0.28.1
Requires-Dist: nonebot2>=2.4.2
Requires-Dist: nonebot-adapter-onebot>=2.4.6
Requires-Dist: playwright>=1.52.0
Requires-Dist: qrcode>=8.2
Requires-Dist: fuzzywuzzy>=0.18.0
Requires-Dist: nonebot-plugin-localstore>=0.7.4
